pygbuttons/Base.py
pygbuttons/Button.py
pygbuttons/Control.py
pygbuttons/DropdownBox.py
pygbuttons/Slider.py
pygbuttons/Text.py
pygbuttons/TextBox.py
pygbuttons/__init__.py
pygbuttons/utils/WeakCache.py
pygbuttons/utils/__init__.py
pygbuttons/utils/alignment.py
pygbuttons-0.9.5.dist-info/LICENSE
pygbuttons-0.9.5.dist-info/METADATA
pygbuttons-0.9.5.dist-info/WHEEL
pygbuttons-0.9.5.dist-info/top_level.txt
pygbuttons-0.9.5.dist-info/RECORD
