Metadata-Version: 2.1
Name: pygbuttons
Version: 0.9.5
Summary: Adds basic UI elements for pygame
Home-page: https://github.com/Jarno-de-Wit/PygButtons
Author: Jarno de Wit
Project-URL: Bug Tracker, https://github.com/Jarno-de-Wit/PygButtons/issues
Classifier: Programming Language :: Python :: 3
Classifier: License :: OSI Approved :: MIT License
Classifier: Operating System :: OS Independent
Requires-Python: >=3.8
License-File: LICENSE
Requires-Dist: pygame>=2.0.1
